django_views/__init__.py
django_views/exceptions.py
django_views/mixins.py
django_views/tests.py
django_views/views.py
django_views-1.0.0.dist-info/DESCRIPTION.rst
django_views-1.0.0.dist-info/METADATA
django_views-1.0.0.dist-info/RECORD
django_views-1.0.0.dist-info/WHEEL
django_views-1.0.0.dist-info/entry_points.txt
django_views-1.0.0.dist-info/metadata.json
django_views-1.0.0.dist-info/top_level.txt
