Metadata-Version: 2.0
Name: django-views
Version: 1.0.0
Summary: A django class based view collection
Home-page: https://github.com/universalyouth/django-views
Author: Younger Shen
Author-email: younger.x.shen@gmail.com
License: MIT
Keywords: django views django-based-views django-views
Platform: UNKNOWN
Classifier: Development Status :: 4 - Beta
Classifier: Intended Audience :: Developers
Classifier: Topic :: Software Development :: Libraries :: Application Frameworks
Classifier: Framework :: Django :: 1.9
Classifier: License :: OSI Approved :: MIT License
Classifier: Programming Language :: Python :: 3.6
Requires-Dist: django (>=1.10)
Requires-Dist: django-filter
Provides-Extra: test
Requires-Dist: coverage; extra == 'test'
